srclicenser/__init__.py
srclicenser/__main__.py
srclicenser/licensers.py
srclicenser/srclicenser.py
srclicenser-0.3.1.dist-info/DESCRIPTION.rst
srclicenser-0.3.1.dist-info/METADATA
srclicenser-0.3.1.dist-info/RECORD
srclicenser-0.3.1.dist-info/WHEEL
srclicenser-0.3.1.dist-info/entry_points.txt
srclicenser-0.3.1.dist-info/metadata.json
srclicenser-0.3.1.dist-info/top_level.txt
