Metadata-Version: 2.0
Name: srclicenser
Version: 0.3.1
Summary: A tool that make sure there have a license header at top of source files
Home-page: https://github.com/starofrainnight/srclicenser
Author: Hong-She Liang
Author-email: starofrainnight@gmail.com
License: Apache Software License
Keywords: srclicenser
Platform: UNKNOWN
Classifier: Development Status :: 2 - Pre-Alpha
Classifier: Intended Audience :: Developers
Classifier: License :: OSI Approved :: Apache Software License
Classifier: Natural Language :: English
Classifier: Programming Language :: Python :: 3
Classifier: Programming Language :: Python :: 3.4
Classifier: Programming Language :: Python :: 3.5
Requires-Dist: chardet
Requires-Dist: click (>=6.0)
